Topsis/__init__.py
Topsis_Yuvraj_102017081-1.1.2.dist-info/LICENSE.txt
Topsis_Yuvraj_102017081-1.1.2.dist-info/METADATA
Topsis_Yuvraj_102017081-1.1.2.dist-info/WHEEL
Topsis_Yuvraj_102017081-1.1.2.dist-info/top_level.txt
Topsis_Yuvraj_102017081-1.1.2.dist-info/RECORD
