Metadata-Version: 2.1
Name: Topsis-Yuvraj-102017081
Version: 1.1.2
Summary: Topsis Package for solving MCDM Problems
Author: Yuvraj Kalsi
Classifier: Programming Language :: Python :: 3
Classifier: License :: OSI Approved :: MIT License
Classifier: Operating System :: OS Independent
License-File: LICENSE.txt
